_restartable/__init__.py
_restartable/procfs.py
_restartable/utils.py
restartable-0.9.1.data/scripts/restartable
restartable-0.9.1.dist-info/LICENSE
restartable-0.9.1.dist-info/METADATA
restartable-0.9.1.dist-info/WHEEL
restartable-0.9.1.dist-info/top_level.txt
restartable-0.9.1.dist-info/RECORD
